odoo/addons/l10n_br_account_withholding/README.rst
odoo/addons/l10n_br_account_withholding/__init__.py
odoo/addons/l10n_br_account_withholding/__manifest__.py
odoo/addons/l10n_br_account_withholding/demo/ir.property.xml
odoo/addons/l10n_br_account_withholding/i18n/l10n_br_account_withholding.pot
odoo/addons/l10n_br_account_withholding/i18n/pt_BR.po
odoo/addons/l10n_br_account_withholding/models/__init__.py
odoo/addons/l10n_br_account_withholding/models/account_move.py
odoo/addons/l10n_br_account_withholding/models/account_move_line.py
odoo/addons/l10n_br_account_withholding/models/l10n_br_fiscal_tax_group.py
odoo/addons/l10n_br_account_withholding/models/res_partner.py
odoo/addons/l10n_br_account_withholding/readme/CONFIGURE.md
odoo/addons/l10n_br_account_withholding/readme/CONTEXT.md
odoo/addons/l10n_br_account_withholding/readme/CONTRIBUTORS.md
odoo/addons/l10n_br_account_withholding/readme/DESCRIPTION.md
odoo/addons/l10n_br_account_withholding/readme/INSTALL.md
odoo/addons/l10n_br_account_withholding/readme/USAGE.md
odoo/addons/l10n_br_account_withholding/static/description/icon.png
odoo/addons/l10n_br_account_withholding/static/description/index.html
odoo/addons/l10n_br_account_withholding/tests/__init__.py
odoo/addons/l10n_br_account_withholding/tests/test_account_wh_invoice.py
odoo/addons/l10n_br_account_withholding/views/account_move.xml
odoo/addons/l10n_br_account_withholding/views/l10n_br_fiscal_tax_group.xml
odoo/addons/l10n_br_account_withholding/views/res_partner.xml
odoo_addon_l10n_br_account_withholding-16.0.3.0.0.dist-info/METADATA
odoo_addon_l10n_br_account_withholding-16.0.3.0.0.dist-info/WHEEL
odoo_addon_l10n_br_account_withholding-16.0.3.0.0.dist-info/top_level.txt
odoo_addon_l10n_br_account_withholding-16.0.3.0.0.dist-info/RECORD
